KOACBIPM/KOACBIPM.py
KOACBIPM/__init__.py
KOACBIPM-0.0.1.dist-info/LICENSE
KOACBIPM-0.0.1.dist-info/METADATA
KOACBIPM-0.0.1.dist-info/WHEEL
KOACBIPM-0.0.1.dist-info/top_level.txt
KOACBIPM-0.0.1.dist-info/RECORD
